miditoolkit/__init__.py
miditoolkit/constants.py
miditoolkit/midi/__init__.py
miditoolkit/midi/containers.py
miditoolkit/midi/parser.py
miditoolkit/pianoroll/__init__.py
miditoolkit/pianoroll/parser.py
miditoolkit/pianoroll/utils.py
miditoolkit/pianoroll/vis.py
pozalabs_miditoolkit-1.2.0.dist-info/LICENSE
pozalabs_miditoolkit-1.2.0.dist-info/WHEEL
pozalabs_miditoolkit-1.2.0.dist-info/METADATA
pozalabs_miditoolkit-1.2.0.dist-info/RECORD
