Metadata-Version: 2.1
Name: pozalabs-miditoolkit
Version: 1.2.0
Summary: A python package for working with MIDI data files. (POZAlabs forked)
License: MIT
Keywords: midi,mir,music
Author: pozalabs
Author-email: contact@pozalabs.com
Requires-Python: >=3.9,<4.0
Classifier: Intended Audience :: Developers
Classifier: Intended Audience :: Science/Research
Classifier: License :: OSI Approved :: MIT License
Classifier: Operating System :: OS Independent
Classifier: Programming Language :: Python :: 3
Classifier: Programming Language :: Python :: 3.9
Classifier: Programming Language :: Python :: 3.10
Classifier: Programming Language :: Python :: 3.10
Classifier: Programming Language :: Python :: 3.11
Classifier: Programming Language :: Python :: 3.9
Classifier: Topic :: Multimedia :: Sound/Audio :: MIDI
Requires-Dist: matplotlib (>=3.5,<4.0)
Requires-Dist: mido (>=1.1.16,<2.0.0)
Requires-Dist: numpy (>=1.19,<2.0)
